[
    {
        "url": "https://www.instagram.com/autoconvocadosuno/",
        "title": "Instagram GEA"
    },
    {
        "url": "https://www.facebook.com/autoconvocadosuno",
        "title": "Facebook GEA"
    },
    {
        "url": "https://www.instagram.com/genero_y_diversidad_gea/",
        "title": "Genero y Diversidad - Instagram"
    },
    {
        "url": "https://www.facebook.com/generoydiversidadgea",
        "title": "Genero y Diversidad - Facebook"
    },
    {
        "url": "https://www.facebook.com/cegresadosuno",
        "title": "Centro de Egresados"
    },
    {
        "url": "https://wa.me/5491133242915",
        "title": "Tutorias Administración"
    },
    {
        "url": "https://www.youtube.com/channel/UCxd-UFY6wChSTF7WJCCFz7g",
        "title": "Youtube GEA"
    },
    {
        "url": "https://docs.google.com/document/d/1E1Y8mML7hAQAJ_0C6RrXLYKjmFqNym4OATaAXUYJvYA/edit?usp=sharing",
        "title": "Tutorías Informática"
    },
    {
        "url": "https://docs.google.com/spreadsheets/d/1yIwkX-2vIMUAFnzGUT4LP2he41JGnovj0UIKqgqHweE/edit?usp=drivesdk",
        "title": "Tarjeta de Beneficios"
    },
    {
        "url": "https://docs.google.com/document/d/1H3S79xQP7XN_yMV-OJLq13wOExNfbtu2JU0rplCHRJQ/edit?usp=sharing",
        "title": "Tutorías Ingeniería"
    },
    {
        "url": "https://docs.google.com/document/d/18x3DSwftcavC-s6ukv2w_3z9bDOhpCHyyw9YVtWoOvY/edit?usp=drivesdk&fbclid=IwAR2uBq8Arzl_w-LN9j6hfactZg7FsjBCJwgnsZ8WcFgX9DmORW0UZfMIFvY",
        "title": "Grupos de la carrera - INFORMATICA"
    },
    {
        "url": "https://autogestion.uno.edu.ar/uno/",
        "title": "SIU Guarani"
    },
    {
        "url": "http://campusvirtual.uno.edu.ar/moodle/",
        "title": "Campus Virtual"
    },
    {
        "url": "https://docs.google.com/document/d/1OxtsP0X-j7xtzUXzaRUOV2JSIj0LwAZOGpcF-_7vX5I/edit?usp=sharing",
        "title": "Grupos de la carrera - ENFERMERIA"
    },
    {
     
        "url": "https://docs.google.com/document/d/10xNX9DHaG1tiYs42p2ltnTZ-UdvWHAxlx1uQqgvYg30/edit?usp=sharing",
        "title": "Grupos de la carrera - ADMINISTRACION"
    },
    {
        "url": "https://chat.whatsapp.com/GDllGTv7zBiGZQHlBapjR3",
        "title": "Grupo de la carrera - INFORMATICA"
    },
    {
        "url": "https://www.facebook.com/groups/informatica.uno.merlo",
        "title": "Grupo de la carrera - FACEBOOK"
    },
    {
        "url": "https://t.me/Informatica_UNO",
        "title": "Grupo de la carrera - INFORMATICA (telegram)"
    },
    {
        "url": "https://discord.gg/DgZnkwf",
        "title": "Discord de la carrera"
    },
    {
        "url": "https://t.me/gnuno_merlo",
        "title": "GNUno"
    },
    {
        "url": "https://chat.whatsapp.com/BV5aRoVPieZ9OKDzSiOd0M",
        "title": "Grupo de la carrera - QUIMICA"
    },
    {
        "url": "https://chat.whatsapp.com/BiQjWxHVnzqLRkD0olthhu?fbclid=IwAR3eGe2Gj0rmksYlJaW2ntTQyCDzfFJQGbgaojFp191LryuFu6dIWVCqx9o",
        "title": "Grupo de la carrera - ADM"
    },
    {
        "url": "https://wa.me/5491139154715",
        "title": "Enfermería 1ro"
    },
    {
        "url": "https://wa.me/5493885212445",
        "title": "Enfermería 2do y 3ro"
    },
    {
        "url": "https://wa.me/5491169364262",
        "title": "Sist. Contables y Conta 1"
    },
    {
        "url": "https://wa.me/5491133242915",
        "title": "Tutorías ADM"
    },
    {
        "url": "https://wa.me/5491156910849",
        "title": "Tutorias Mate 1 y 2"
    },
    {
        "url": "https://chat.whatsapp.com/FU5uDcZQBY4JrUYClg2Tgj",
        "title": "Ingles"
    },
    {
        "url": "https://drive.google.com/file/d/1BZP-SuGjH0kfXjkXCRwBaqim86I-8zb2/view?usp=drivesdk",
        "title": "Resolucion de Cursada Virtual"
    },
    {
        "url": "https://drive.google.com/file/d/0B41zO4qldC4eaHJ5OHFYWFp0UFk/view?usp=drivesdk",
        "title": "Estatuto del Centro de Estudiantes"
    },
    {
        "url": "https://drive.google.com/file/d/1OPWqtycr2VWqSKoAK1w7IeXs5wxk8A6M/view?usp=drivesdk",
        "title": "Protocolo de Genero"
    },
    {
        "url": "https://drive.google.com/file/d/0B2S9Bo8h-kwFSV92ZU5melNIbGM/view?usp=drivesdk",
        "title": "Reglamento de Ayudante de Catedra"
    },
    {
        "url": "https://drive.google.com/file/d/0B41zO4qldC4eSzZxWTdhMU45dkk/view?usp=drivesdk",
        "title": "Reglamento Electoral"
    },
    {
        "url": "https://drive.google.com/file/d/1GRgITeadkmpYh1lCa6DGYJXd0jeiKs_L/view?usp=drivesdk",
        "title": "Reglamento de Examenes Virtuales"
    },
    {
        "url": "https://drive.google.com/file/d/0B2S9Bo8h-kwFeEFIR19jWUpOdjQ/view?usp=drivesdk",
        "title": "Reglamento de Alumnos"
    }
]